baangt/__init__.py
baangt/hookSpecs.py
baangt/reports.py
baangt/TestCase/TestCaseMaster.py
baangt/TestCase/__init__.py
baangt/TestCaseSequence/TestCaseSequenceMaster.py
baangt/TestCaseSequence/TestCaseSequenceParallel.py
baangt/TestCaseSequence/__init__.py
baangt/TestDataGenerator/TestDataGenerator.py
baangt/TestDataGenerator/__init__.py
baangt/TestSteps/AddressCreation.py
baangt/TestSteps/Exceptions.py
baangt/TestSteps/RandomValues.py
baangt/TestSteps/TestStepMaster.py
baangt/TestSteps/__init__.py
baangt/TestSteps/DropsApp/Login_API.py
baangt/TestSteps/DropsApp/__init__.py
baangt/base/AddressCreate.py
baangt/base/ApiHandling.py
baangt/base/BrowserFactory.py
baangt/base/Cleanup.py
baangt/base/CliAndInteractive.py
baangt/base/CustGlobalConstants.py
baangt/base/DataBaseORM.py
baangt/base/DownloadFolderMonitoring.py
baangt/base/Faker.py
baangt/base/FilesOpen.py
baangt/base/GlobalConstants.py
baangt/base/HandleDatabase.py
baangt/base/IBAN.py
baangt/base/ODataHandling.py
baangt/base/PDFCompare.py
baangt/base/PathManagement.py
baangt/base/ProxyRotate.py
baangt/base/ResultsBrowser.py
baangt/base/RuntimeStatistics.py
baangt/base/SOAPHandling.py
baangt/base/TestRunExcelImporter.py
baangt/base/TestRunUtils.py
baangt/base/Utils.py
baangt/base/__init__.py
baangt/base/BrowserHandling/BrowserHandling.py
baangt/base/BrowserHandling/BrowserHelperFunction.py
baangt/base/BrowserHandling/WebdriverFunctions.py
baangt/base/BrowserHandling/__init__.py
baangt/base/BrowserHandling/hookImpls.py
baangt/base/ExportResults/Append2BaseXLS.py
baangt/base/ExportResults/ExportConfluence.py
baangt/base/ExportResults/ExportResults.py
baangt/base/ExportResults/SendStatistics.py
baangt/base/ExportResults/__init__.py
baangt/base/ExportResults/hookImpls.py
baangt/base/SendReports/__init__.py
baangt/base/SendReports/mailer.py
baangt/base/TestRun/ClassesForObjects.py
baangt/base/TestRun/TestRun.py
baangt/base/TestRun/__init__.py
baangt/base/TestRun/hookImpls.py
baangt/base/Timing/Timing.py
baangt-1.2.7.dist-info/LICENSE
baangt-1.2.7.dist-info/METADATA
baangt-1.2.7.dist-info/WHEEL
baangt-1.2.7.dist-info/top_level.txt
baangt-1.2.7.dist-info/RECORD
