Metadata-Version: 2.1
Name: baangt
Version: 1.2.7
Summary: Open source Test Automation Suite for MacOS, Windows, Linux
Home-page: https://baangt.org
Author: Bernhard Buhl
Author-email: info@baangt.org
License: UNKNOWN
Platform: UNKNOWN
Classifier: Programming Language :: Python :: 3
Classifier: License :: OSI Approved :: MIT License
Classifier: Operating System :: OS Independent
Requires-Python: >=3.6
Requires-Dist: Appium-Python-Client
Requires-Dist: beautifulsoup4
Requires-Dist: browsermob-proxy
Requires-Dist: dataclasses
Requires-Dist: dataclasses-json
Requires-Dist: faker
Requires-Dist: gevent
Requires-Dist: jinja2
Requires-Dist: lxml
Requires-Dist: openpyxl
Requires-Dist: pandas
Requires-Dist: Pillow
Requires-Dist: pluggy
Requires-Dist: pyperclip
Requires-Dist: pyQT5 (==5.14.2)
Requires-Dist: requests
Requires-Dist: requests-toolbelt
Requires-Dist: schwifty
Requires-Dist: selenium
Requires-Dist: sqlalchemy
Requires-Dist: urllib3
Requires-Dist: psutil
Requires-Dist: pymsteams
Requires-Dist: slack-webhook
Requires-Dist: xl2dict
Requires-Dist: xlrd3
Requires-Dist: xlsxwriter
Requires-Dist: atlassian-python-api
Requires-Dist: icopy2xls
Requires-Dist: xlsclone
